snid_sage/__init__.py
snid_sage/_version.py
snid_sage/images/icon.png
snid_sage/images/tick_white.svg
snid_sage/images/twemoji/1f370.svg
snid_sage/images/twemoji/1f3a8.svg
snid_sage/images/twemoji/1f3af.svg
snid_sage/images/twemoji/1f40c.svg
snid_sage/images/twemoji/1f441.svg
snid_sage/images/twemoji/1f4be.svg
snid_sage/images/twemoji/1f4c4.svg
snid_sage/images/twemoji/1f4c8.svg
snid_sage/images/twemoji/1f4c9.svg
snid_sage/images/twemoji/1f4ca.svg
snid_sage/images/twemoji/1f4cb.svg
snid_sage/images/twemoji/1f4f7.svg
snid_sage/images/twemoji/1f504.svg
snid_sage/images/twemoji/1f50d.svg
snid_sage/images/twemoji/1f527.svg
snid_sage/images/twemoji/1f534.svg
snid_sage/images/twemoji/1f5a5.svg
snid_sage/images/twemoji/1f5d1.svg
snid_sage/images/twemoji/1f6a8.svg
snid_sage/images/twemoji/1f6ab.svg
snid_sage/images/twemoji/1f6f0.svg
snid_sage/images/twemoji/1f916.svg
snid_sage/images/twemoji/2139.svg
snid_sage/images/twemoji/2696.svg
snid_sage/images/twemoji/26a0.svg
snid_sage/images/twemoji/26a1.svg
snid_sage/images/twemoji/2705.svg
snid_sage/images/twemoji/2728.svg
snid_sage/images/twemoji/274c.svg
snid_sage/images/twemoji/2753.svg
snid_sage/images/twemoji/2b50.svg
snid_sage/interfaces/__init__.py
snid_sage/interfaces/cli/__init__.py
snid_sage/interfaces/cli/batch.py
snid_sage/interfaces/cli/config.py
snid_sage/interfaces/cli/identify.py
snid_sage/interfaces/cli/main.py
snid_sage/interfaces/cli/templates.py
snid_sage/interfaces/gui/__init__.py
snid_sage/interfaces/gui/launcher.py
snid_sage/interfaces/gui/pyside6_gui.py
snid_sage/interfaces/gui/components/__init__.py
snid_sage/interfaces/gui/components/analysis/__init__.py
snid_sage/interfaces/gui/components/analysis/analysis_menu_manager.py
snid_sage/interfaces/gui/components/dialogs/__init__.py
snid_sage/interfaces/gui/components/events/pyside6_event_handlers.py
snid_sage/interfaces/gui/components/plots/__init__.py
snid_sage/interfaces/gui/components/plots/enhanced_plot_widget.py
snid_sage-1.1.1.dist-info/licenses/LICENSE
snid_sage-1.1.1.dist-info/METADATA
snid_sage-1.1.1.dist-info/WHEEL
snid_sage-1.1.1.dist-info/entry_points.txt
snid_sage-1.1.1.dist-info/top_level.txt
snid_sage-1.1.1.dist-info/RECORD
