Metadata-Version: 2.4
Name: snid-sage
Version: 1.1.1
Summary: SNID SAGE - SuperNova IDentification – Spectral Analysis and Guided Exploration
Author-email: Fiorenzo Stoppa <fiorenzo.stoppa@physics.ox.ac.uk>
Maintainer-email: Fiorenzo Stoppa <fiorenzo.stoppa@physics.ox.ac.uk>
License-Expression: MIT
Project-URL: Homepage, https://github.com/FiorenSt/SNID-SAGE
Project-URL: Documentation, https://fiorenst.github.io/SNID-SAGE
Project-URL: Repository, https://github.com/FiorenSt/SNID-SAGE.git
Project-URL: Bug Reports, https://github.com/FiorenSt/SNID-SAGE/issues
Project-URL: Download, https://github.com/FiorenSt/SNID-SAGE/archive/refs/heads/main.zip
Keywords: astronomy,supernova,spectrum,analysis,snid,machine-learning
Classifier: Development Status :: 5 - Production/Stable
Classifier: Intended Audience :: Science/Research
Classifier: Operating System :: OS Independent
Classifier: Programming Language :: Python :: 3
Classifier: Programming Language :: Python :: 3.8
Classifier: Programming Language :: Python :: 3.9
Classifier: Programming Language :: Python :: 3.10
Classifier: Programming Language :: Python :: 3.11
Classifier: Programming Language :: Python :: 3.12
Classifier: Topic :: Scientific/Engineering :: Astronomy
Classifier: Topic :: Scientific/Engineering :: Artificial Intelligence
Classifier: Natural Language :: English
Requires-Python: >=3.8
License-File: LICENSE
Requires-Dist: numpy>=1.19.0
Requires-Dist: scipy>=1.7.0
Requires-Dist: h5py>=2.10.0
Requires-Dist: pandas>=1.1.0
Requires-Dist: matplotlib>=3.3.0
Requires-Dist: astropy>=4.0.0
Requires-Dist: scikit-learn>=1.0.0
Requires-Dist: requests>=2.25.0
Requires-Dist: PySide6<6.9.1,>=6.7
Requires-Dist: pyqtgraph>=0.13.0
Requires-Dist: packaging>=20.0
Requires-Dist: platformdirs>=3.0.0
Provides-Extra: dev
Requires-Dist: pytest>=6.0.0; extra == "dev"
Requires-Dist: pytest-cov>=2.10.0; extra == "dev"
Requires-Dist: black>=21.0.0; extra == "dev"
Requires-Dist: flake8>=3.8.0; extra == "dev"
Requires-Dist: mypy>=0.800; extra == "dev"
Requires-Dist: mkdocs>=1.5; extra == "dev"
Requires-Dist: mkdocs-material>=9.0; extra == "dev"
Requires-Dist: sphinx>=4.0.0; extra == "dev"
Requires-Dist: sphinx-rtd-theme>=1.0.0; extra == "dev"
Requires-Dist: twine>=4.0.0; extra == "dev"
Requires-Dist: build>=0.8.0; extra == "dev"
Dynamic: license-file
